optunahub/__init__.py
optunahub/_conf.py
optunahub/hub.py
optunahub/py.typed
optunahub/version.py
optunahub/benchmarks/__init__.py
optunahub/benchmarks/_base_problem.py
optunahub/benchmarks/_constrained_mixin.py
optunahub/samplers/__init__.py
optunahub/samplers/_simple_base.py
optunahub-0.4.0.dist-info/LICENSE
optunahub-0.4.0.dist-info/METADATA
optunahub-0.4.0.dist-info/WHEEL
optunahub-0.4.0.dist-info/top_level.txt
optunahub-0.4.0.dist-info/RECORD
