Metadata-Version: 2.1
Name: optunahub
Version: 0.4.0
Summary: OptunaHub
Author: Optuna team
Project-URL: homepage, https://hub.optuna.org/
Project-URL: repository, https://github.com/optuna/optunahub
Project-URL: documentation, https://optuna.github.io/optunahub/
Project-URL: bugtracker, https://github.com/optuna/optunahub/issues
Classifier: Development Status :: 5 - Production/Stable
Classifier: Intended Audience :: Science/Research
Classifier: Intended Audience :: Developers
Classifier: License :: OSI Approved :: MIT License
Classifier: Programming Language :: Python :: 3
Classifier: Programming Language :: Python :: 3.8
Classifier: Programming Language :: Python :: 3.9
Classifier: Programming Language :: Python :: 3.10
Classifier: Programming Language :: Python :: 3.11
Classifier: Programming Language :: Python :: 3.12
Classifier: Programming Language :: Python :: 3 :: Only
Classifier: Topic :: Scientific/Engineering
Classifier: Topic :: Scientific/Engineering :: Mathematics
Classifier: Topic :: Scientific/Engineering :: Artificial Intelligence
Classifier: Topic :: Software Development
Classifier: Topic :: Software Development :: Libraries
Classifier: Topic :: Software Development :: Libraries :: Python Modules
Requires-Python: >=3.8
License-File: LICENSE
Requires-Dist: optuna
Requires-Dist: GitPython
Requires-Dist: PyGithub>=1.59
Provides-Extra: checking
Requires-Dist: pre-commit; extra == "checking"
Requires-Dist: mypy; extra == "checking"
Requires-Dist: ruff; extra == "checking"
Requires-Dist: types-toml; extra == "checking"
Provides-Extra: docs
Requires-Dist: plotly; extra == "docs"
Requires-Dist: sphinx; extra == "docs"
Requires-Dist: sphinx-rtd-theme; extra == "docs"
Requires-Dist: sphinx-gallery; extra == "docs"
Requires-Dist: matplotlib; extra == "docs"
Requires-Dist: optuna; extra == "docs"
Requires-Dist: optunahub; extra == "docs"
Provides-Extra: test
Requires-Dist: coverage; extra == "test"
Requires-Dist: pytest; extra == "test"
